Metadata-Version: 2.1
Name: mssqlgenerator
Version: 1.2
Summary: Simple T-SQL query generator based on JSON parameters.
Home-page: https://github.com/kamiljaved/mssqlgenerator
Author: Kamil Javed
Author-email: kamil.javed@footmetrics.io
Requires-Python: >=3.8.10
License-File: LICENSE
